Orange3_Network_zh-1.4.2-py3.7-nspkg.pth
orangecontrib/network/__init__.py
orangecontrib/network/_fr_layout.cpython-37m-darwin.so
orangecontrib/network/setup.py
orangecontrib/network/network/__init__.py
orangecontrib/network/network/base.py
orangecontrib/network/network/community.py
orangecontrib/network/network/generate.py
orangecontrib/network/network/readwrite.py
orangecontrib/network/network/twomode.py
orangecontrib/network/networks/airtraffic.net
orangecontrib/network/networks/airtraffic_items.tab
orangecontrib/network/networks/davis.net
orangecontrib/network/networks/davis.tsv
orangecontrib/network/networks/dicty_publication.net
orangecontrib/network/networks/dicty_publication_edges.tab
orangecontrib/network/networks/dicty_publication_items.tab
orangecontrib/network/networks/lastfm.net
orangecontrib/network/networks/lastfm.tab
orangecontrib/network/networks/lastfm_all.tab
orangecontrib/network/networks/lastfm_tags.tab
orangecontrib/network/networks/leu_by_genesets.net
orangecontrib/network/networks/leu_by_genesets_items.tab
orangecontrib/network/networks/leu_by_pmid.net
orangecontrib/network/networks/leu_by_pmid_items.tab
orangecontrib/network/networks/leu_huttenhower_a.net
orangecontrib/network/networks/leu_huttenhower_a_items.tab
orangecontrib/network/networks/makeNetworkList.py
orangecontrib/network/networks/mips_c2_cp_leu.net
orangecontrib/network/networks/mips_c2_cp_leu_items.tab
orangecontrib/network/networks/network_info.tab
orangecontrib/network/widgets/OWNxAnalysis.py
orangecontrib/network/widgets/OWNxClustering.py
orangecontrib/network/widgets/OWNxExplorer.py
orangecontrib/network/widgets/OWNxFile.py
orangecontrib/network/widgets/OWNxFromDistances.py
orangecontrib/network/widgets/OWNxGenerator.py
orangecontrib/network/widgets/OWNxGroups.py
orangecontrib/network/widgets/OWNxSave.py
orangecontrib/network/widgets/__init__.py
orangecontrib/network/widgets/graphview.py
orangecontrib/network/widgets/ownxsinglemode.py
Orange3_Network_zh-1.4.2.dist-info/COPYING
Orange3_Network_zh-1.4.2.dist-info/LICENSE
Orange3_Network_zh-1.4.2.dist-info/METADATA
Orange3_Network_zh-1.4.2.dist-info/WHEEL
Orange3_Network_zh-1.4.2.dist-info/entry_points.txt
Orange3_Network_zh-1.4.2.dist-info/namespace_packages.txt
Orange3_Network_zh-1.4.2.dist-info/top_level.txt
Orange3_Network_zh-1.4.2.dist-info/RECORD
