Metadata-Version: 2.1
Name: Orange3-Network-zh
Version: 1.4.2
Summary: Networks add-on for Orange 3 data mining software package.
Home-page: https://github.com/biolab/orange3-network
Author: Laboratory of Bioinformatics, FRI UL
Author-email: info@biolab.si
License: GPLv3
Keywords: network,network analysis,network layout,network visualization,data mining,machine learning,artificial intelligence,orange,orange3 add-on
Platform: UNKNOWN
Classifier: Development Status :: 4 - Beta
Classifier: Environment :: X11 Applications :: Qt
Classifier: Environment :: Console
Classifier: Environment :: Plugins
Classifier: Programming Language :: Python
Classifier: License :: OSI Approved :: GNU General Public License v3 or later (GPLv3+)
Classifier: Operating System :: OS Independent
Classifier: Topic :: Scientific/Engineering :: Artificial Intelligence
Classifier: Topic :: Scientific/Engineering :: Visualization
Classifier: Topic :: Software Development :: Libraries :: Python Modules
Classifier: Intended Audience :: Education
Classifier: Intended Audience :: Science/Research
Classifier: Intended Audience :: Developers
Requires-Dist: pyqtgraph (>=0.9.10)
Requires-Dist: numpy (>=1.8.0)
Requires-Dist: Orange3-zh (>=3.20)
Provides-Extra: gui
Requires-Dist: AnyQt ; extra == 'gui'
Provides-Extra: rest
Requires-Dist: numpydoc ; extra == 'rest'
